benchmarks/__init__.py
benchmarks/benchmark_serving.py
benchmarks/eval_accuracy.py
jetstream/__init__.py
jetstream/core/__init__.py
jetstream/core/config_lib.py
jetstream/core/orchestrator.py
jetstream/core/server_lib.py
jetstream/core/implementations/__init__.py
jetstream/core/implementations/mock/__init__.py
jetstream/core/implementations/mock/config.py
jetstream/core/implementations/mock/server.py
jetstream/core/metrics/__init__.py
jetstream/core/metrics/prometheus.py
jetstream/core/proto/__init__.py
jetstream/core/proto/jetstream_pb2.py
jetstream/core/proto/jetstream_pb2_grpc.py
jetstream/core/utils/__init__.py
jetstream/core/utils/async_multifuture.py
jetstream/core/utils/return_sample.py
jetstream/engine/__init__.py
jetstream/engine/engine_api.py
jetstream/engine/mock_engine.py
jetstream/engine/mock_utils.py
jetstream/engine/token_utils.py
jetstream/engine/tokenizer_api.py
jetstream/engine/tokenizer_pb2.py
jetstream/engine/tokenizer_pb2_grpc.py
jetstream/tests/__init__.py
jetstream/tests/core/__init__.py
jetstream/tests/core/test_config_lib.py
jetstream/tests/core/test_orchestrator.py
jetstream/tests/core/test_server.py
jetstream/tests/engine/__init__.py
jetstream/tests/engine/test_mock_engine.py
jetstream/tests/engine/test_token_utils.py
jetstream/tests/engine/test_utils.py
jetstream/third_party/__init__.py
jetstream/third_party/llama3/__init__.py
jetstream/third_party/llama3/llama3_tokenizer.py
google_jetstream-0.2.2.dist-info/AUTHORS
google_jetstream-0.2.2.dist-info/LICENSE
google_jetstream-0.2.2.dist-info/METADATA
google_jetstream-0.2.2.dist-info/WHEEL
google_jetstream-0.2.2.dist-info/top_level.txt
google_jetstream-0.2.2.dist-info/RECORD
