Metadata-Version: 2.1
Name: google-jetstream
Version: 0.2.2
Summary: JetStream is a throughput and memory optimized engine for LLM inference on XLA devices, starting with TPUs (and GPUs in future -- PRs welcome).
Home-page: https://github.com/google/JetStream
Author: Google LLC
Classifier: Programming Language :: Python :: 3.10
Classifier: License :: OSI Approved :: Apache Software License
Classifier: Operating System :: OS Independent
Requires-Python: >=3.10
License-File: LICENSE
License-File: AUTHORS
Requires-Dist: absl-py
Requires-Dist: coverage
Requires-Dist: flax
Requires-Dist: grpcio
Requires-Dist: jax
Requires-Dist: jaxlib
Requires-Dist: numpy
Requires-Dist: portpicker
Requires-Dist: prometheus-client
Requires-Dist: pytest
Requires-Dist: seqio
Requires-Dist: tiktoken
Requires-Dist: blobfile
Requires-Dist: parameterized
Requires-Dist: shortuuid
